qluster/__init__.py
qluster/qluster.py
qluster-0.2.0.dist-info/LICENSE
qluster-0.2.0.dist-info/METADATA
qluster-0.2.0.dist-info/WHEEL
qluster-0.2.0.dist-info/top_level.txt
qluster-0.2.0.dist-info/RECORD
