Metadata-Version: 2.1
Name: qluster
Version: 0.2.0
Summary: Quick clusters of merging binary black holes
Author-email: Matthew Mould <mattdmould@gmail.com>
Project-URL: Homepage, https://github.com/mdmould/qluster
Classifier: Programming Language :: Python :: 3
Classifier: License :: OSI Approved :: MIT License
Classifier: Operating System :: OS Independent
Requires-Python: >=3.9
License-File: LICENSE
Requires-Dist: numpy
Requires-Dist: precession
Requires-Dist: tqdm
Requires-Dist: parabar
Requires-Dist: h5ify
